inbound/__init__.py
inbound/__main__.py
inbound/core/__init__.py
inbound/core/bookmark_service.py
inbound/core/connection_factory.py
inbound/core/connection_loader.py
inbound/core/dbt_profile.py
inbound/core/environment.py
inbound/core/job_factory.py
inbound/core/job_id.py
inbound/core/job_result.py
inbound/core/jobs.py
inbound/core/logging.py
inbound/core/metadata.py
inbound/core/models.py
inbound/core/package.py
inbound/core/publisher.py
inbound/core/secrets.py
inbound/core/settings.py
inbound/core/transformer.py
inbound/core/utils.py
inbound/dbt_artifacts/__init__.py
inbound/dbt_artifacts/graph.py
inbound/dbt_artifacts/manifest.py
inbound/dbt_artifacts/models/__init__.py
inbound/dbt_artifacts/models/manifest_model_v5.py
inbound/dbt_artifacts/models/manifest_model_v6.py
inbound/dbt_artifacts/models/manifest_model_v7.py
inbound/framework/__init__.py
inbound/framework/cli.py
inbound/plugins/__init__.py
inbound/plugins/common.py
inbound/plugins/utils.py
inbound/plugins/connections/__init__.py
inbound/plugins/connections/bigquery.py
inbound/plugins/connections/connection.py
inbound/plugins/connections/cx_oracle.py
inbound/plugins/connections/duckdb.py
inbound/plugins/connections/file.py
inbound/plugins/connections/gcs.py
inbound/plugins/connections/oracle.py
inbound/plugins/connections/postgres.py
inbound/plugins/connections/snowflake.py
inbound/plugins/connections/sqlalchemy.py
inbound-0.0.4.dist-info/METADATA
inbound-0.0.4.dist-info/WHEEL
inbound-0.0.4.dist-info/entry_points.txt
inbound-0.0.4.dist-info/top_level.txt
inbound-0.0.4.dist-info/RECORD
